netcupctl/__init__.py
netcupctl/__main__.py
netcupctl/auth.py
netcupctl/cli.py
netcupctl/client.py
netcupctl/config.py
netcupctl/output.py
netcupctl/spec_manager.py
netcupctl/commands/__init__.py
netcupctl/commands/custom_images.py
netcupctl/commands/custom_isos.py
netcupctl/commands/disks.py
netcupctl/commands/failover_ips.py
netcupctl/commands/firewall.py
netcupctl/commands/firewall_policies.py
netcupctl/commands/guest_agent.py
netcupctl/commands/helpers.py
netcupctl/commands/images.py
netcupctl/commands/interfaces.py
netcupctl/commands/iso.py
netcupctl/commands/logs.py
netcupctl/commands/maintenance.py
netcupctl/commands/metrics.py
netcupctl/commands/rdns.py
netcupctl/commands/rescue.py
netcupctl/commands/servers.py
netcupctl/commands/snapshots.py
netcupctl/commands/spec.py
netcupctl/commands/ssh_keys.py
netcupctl/commands/storage.py
netcupctl/commands/tasks.py
netcupctl/commands/user_logs.py
netcupctl/commands/users.py
netcupctl/commands/validators.py
netcupctl/commands/vlans.py
netcupctl-0.5.0.dist-info/licenses/LICENSE.md
netcupctl-0.5.0.dist-info/METADATA
netcupctl-0.5.0.dist-info/WHEEL
netcupctl-0.5.0.dist-info/entry_points.txt
netcupctl-0.5.0.dist-info/top_level.txt
netcupctl-0.5.0.dist-info/RECORD
