Metadata-Version: 2.4
Name: netcupctl
Version: 0.5.0
Summary: CLI client for netcup Server Control Panel REST API
Author: netcupctl contributors
License: MIT
Project-URL: Homepage, https://github.com/DS09AT/netcupctl
Project-URL: Documentation, https://github.com/DS09AT/netcupctl/blob/main/README.md
Project-URL: Repository, https://github.com/DS09AT/netcupctl
Project-URL: Issues, https://github.com/DS09AT/netcupctl/issues
Classifier: Development Status :: 3 - Alpha
Classifier: Intended Audience :: Developers
Classifier: Intended Audience :: System Administrators
Classifier: License :: OSI Approved :: MIT License
Classifier: Programming Language :: Python :: 3
Classifier: Programming Language :: Python :: 3.8
Classifier: Programming Language :: Python :: 3.9
Classifier: Programming Language :: Python :: 3.10
Classifier: Programming Language :: Python :: 3.11
Classifier: Programming Language :: Python :: 3.12
Classifier: Topic :: System :: Systems Administration
Requires-Python: >=3.8
License-File: LICENSE.md
Requires-Dist: click>=8.0.0
Requires-Dist: requests>=2.31.0
Requires-Dist: rich>=13.0.0
Requires-Dist: pyyaml>=6.0.0
Provides-Extra: dev
Requires-Dist: pytest>=7.0.0; extra == "dev"
Requires-Dist: pytest-cov>=4.0.0; extra == "dev"
Requires-Dist: requests-mock>=1.11.0; extra == "dev"
Requires-Dist: pylint>=3.0.0; extra == "dev"
Dynamic: license-file
